[
  {
    "poster": {
      "poster_name": "Mihail Stingaci",
      "poster_handle": "mst"
    },
    "time_stamp": "2022-09-26 04:18:59",
    "text": "I made the proposed changes, now the last banner is replaced by a span and I can't understand where it is pulled from."
  },
  {
    "text": "",
    "time_stamp": "2022-09-26 04:19:47"
  },
  {
    "text": "",
    "time_stamp": "2022-09-26 04:19:51"
  },
  {
    "poster": {
      "poster_name": "Mihail Stingaci",
      "poster_handle": "mst"
    },
    "time_stamp": "2022-09-26 04:21:30",
    "text": "When I open in preview, everything is ok, but when I save the changes, then this problem appears on the site"
  },
  {
    "text": "",
    "time_stamp": "2022-09-26 04:23:08"
  },
  {
    "poster": {
      "poster_name": "Nicholas Decker - Level -22",
      "poster_handle": "nickdeckerdevs"
    },
    "time_stamp": "2022-09-26 04:32:09",
    "text": "Can you provide a preview link?"
  },
  {
    "poster": {
      "poster_name": "Nicholas Decker - Level -22",
      "poster_handle": "nickdeckerdevs"
    },
    "time_stamp": "2022-09-26 04:32:55",
    "text": "Actually what is the issue you are having now. "
  },
  {
    "poster": {
      "poster_name": "Mihail Stingaci",
      "poster_handle": "mst"
    },
    "time_stamp": "2022-09-26 04:51:09",
    "text": "the problem is that my last article is replaced with this Knowledge hub (which is actually the link to this page)"
  },
  {
    "poster": {
      "poster_name": "Nicholas Decker - Level -22",
      "poster_handle": "nickdeckerdevs"
    },
    "time_stamp": "2022-09-26 04:53:24",
    "text": "So your 4th item in the repeater is not what shows up here?"
  },
  {
    "poster": {
      "poster_name": "Mihail Stingaci",
      "poster_handle": "mst"
    },
    "time_stamp": "2022-09-26 04:53:57",
    "text": "yes"
  },
  {
    "poster": {
      "poster_name": "Nicholas Decker - Level -22",
      "poster_handle": "nickdeckerdevs"
    },
    "time_stamp": "2022-09-26 04:55:10",
    "text": "Is this a module in a page or are you using the design manager preview still?"
  },
  {
    "poster": {
      "poster_name": "Nicholas Decker - Level -22",
      "poster_handle": "nickdeckerdevs"
    },
    "time_stamp": "2022-09-26 04:55:26",
    "text": "It sounds like there is some caching problem "
  },
  {
    "poster": {
      "poster_name": "Mihail Stingaci",
      "poster_handle": "mst"
    },
    "time_stamp": "2022-09-26 04:55:31",
    "text": "Is in the page"
  },
  {
    "poster": {
      "poster_name": "Nicholas Decker - Level -22",
      "poster_handle": "nickdeckerdevs"
    },
    "time_stamp": "2022-09-26 04:55:43",
    "text": "And you should use the preview link from the page editor "
  },
  {
    "poster": {
      "poster_name": "Nicholas Decker - Level -22",
      "poster_handle": "nickdeckerdevs"
    },
    "time_stamp": "2022-09-26 04:56:25",
    "text": "The link that gives ?hspreview stuff in the url"
  },
  {
    "poster": {
      "poster_name": "Mihail Stingaci",
      "poster_handle": "mst"
    },
    "time_stamp": "2022-09-26 04:56:50",
    "text": "in preview link everithing is ok"
  },
  {
    "poster": {
      "poster_name": "Mihail Stingaci",
      "poster_handle": "mst"
    },
    "time_stamp": "2022-09-26 04:57:50",
    "text": "These foreign elements do not appear there."
  },
  {
    "text": "In fact, this is the fifth element in the repeater that is hidden and appears when we press the arrows.",
    "time_stamp": "2022-09-26 05:02:28"
  },
  {
    "poster": {
      "poster_name": "Bradley",
      "poster_handle": "bradley554"
    },
    "time_stamp": "2022-09-26 09:01:46",
    "text": "Did anyone ever make a Firefox version of the Developer Extension?"
  },
  {
    "poster": {
      "poster_name": "Mihail Stingaci",
      "poster_handle": "mst"
    },
    "time_stamp": "2022-09-27 00:04:40",
    "text": "Hello, I tried another approach to this problem, I changed the code in question with another one from another fully functional section, but the \"Knowledge hub\" element remains only with small style changes. Where can I look, can you guide me?"
  },
  {
    "poster": {
      "poster_name": "Mihail Stingaci",
      "poster_handle": "mst"
    },
    "time_stamp": "2022-09-27 00:07:59",
    "text": "I have one more question, is it possible to stylize the Cookie banner?"
  }
]