[
  {
    "poster": {
      "poster_name": "Chul Christian Aamodt",
      "poster_handle": "chul.aamodt"
    },
    "time_stamp": "2021-12-28 14:30:10",
    "text": "Hi!\n\nI try to implement the event calendar (<https://designers.HubSpot.com/code-gallery/entry/founders/katelynae-hubdb-event-listing>), but I do not get any data presented in the output.\n\nThe table ID is 5314127\n\nHere´s the output: <https://arrangement.europower-energi.no/-temporary-slug-0b75e956-b65d-47b9-bc2a-9ff4d7abb2b1>\n\nHere´s the code from a template:\n\n{% if dynamic_page_hubdb_row%}\n&lt;div class=\"event-banner-area\" style=\"background-image: url('{{ dynamic_page_hubdb_row.image.url }}'); background-size: cover;\"&gt;\n  &lt;div class=\"event-header-container\"&gt;\n    &lt;div class=\"event-header-content\"&gt;\n      &lt;div class=\"event-header-text\"&gt;\n        &lt;h1&gt;\n          {{ dynamic_page_hubdb_row.name }}\n        &lt;/h1&gt;\n        &lt;p&gt;\n          {{ dynamic_page_hubdb_row.date|datetimeformat('%A, %B %e, %Y') }} | {{ dynamic_page_hubdb_row.region }}\n        &lt;/p&gt;\n      &lt;/div&gt;\n    &lt;/div&gt;\n  &lt;/div&gt;\n  &lt;div class=\"event-banner-edge\"&gt;\n    &lt;svg viewBox=\"0 0 500 50\" preserveAspectRatio=\"xMinYMin meet\"&gt;\n      &lt;path d=\"M0,50 L0,4 C95,-23 285,115 500,2 L500,50 L0,50 Z\" style=\"stroke: none; fill: #fff;\"&gt;&lt;/path&gt;\n    &lt;/svg&gt;\n\n  &lt;/div&gt;\n&lt;/div&gt;\n&lt;div class=\"events-listing container\"&gt;\n  &lt;div class=\"event-details-container\"&gt;\n    &lt;div class=\"event-section\"&gt;\n      &lt;hr&gt;\n      &lt;h2 class=\"event-section-header\"&gt;\n        What to Expect\n      &lt;/h2&gt;\n      &lt;p&gt;\n        {{ dynamic_page_hubdb_row.description }}\n      &lt;/p&gt;\n    &lt;/div&gt;\n    &lt;div class=\"event-section\"&gt;\n      &lt;hr&gt;\n      &lt;h2 class=\"event-section-header\"&gt;\n        Agenda\n      &lt;/h2&gt;\n      &lt;p&gt;\n         {{ dynamic_page_hubdb_row.agenda }}\n      &lt;/p&gt;\n\n    &lt;/div&gt;\n    &lt;div class=\"event-section\"&gt;\n      &lt;hr&gt;\n      &lt;h2 class=\"event-section-header\"&gt;\n        Featured Speaker\n      &lt;/h2&gt;\n      &lt;img src=\"{{ dynamic_page_hubdb_row.speaker_image.url }}\" class=\"speaker-image\" /&gt;\n      {{ dynamic_page_hubdb_row.speakers }}\n    &lt;/div&gt;\n  &lt;/div&gt;\n&lt;/div&gt;\n{% elif module.hubdb_table %}\n{% set table = hubdb_table_rows(module.hubdb_table, queryparam) %}\n&lt;div class=\"events container\"&gt;\n  &lt;div class=\"events-results\"&gt;\n    {% for row in table %}\n    &lt;div class=\"event-item\"&gt;\n      &lt;div class=\"event-item-content\"&gt;\n        &lt;div class=\"event-image-container\"&gt;\n          &lt;a href=\"{{ request.path }}/{{ row.hs_path }}\"&gt;\n            &lt;img src=\"{{ row.image.url }}\" /&gt;\n          &lt;/a&gt;\n        &lt;/div&gt;\n        &lt;div class=\"event-text-container\" &gt;\n          &lt;h4&gt;\n            {{ row.name }}\n          &lt;/h4&gt;\n          &lt;p&gt;\n            {{ row.date|datetimeformat('%e of %B %Y') }}, {{ row.region }}\n          &lt;/p&gt;\n          &lt;a href=\"{{ request.path }}/{{ row.hs_path }}\" class=\"event-cta\"&gt;Learn more »&lt;/a&gt;\n        &lt;/div&gt;\n      &lt;/div&gt;\n    &lt;/div&gt;\n    {% endfor %}\n  &lt;/div&gt;\n&lt;/div&gt;\n{% endif %} (edited) \n\n\n*<http://arrangement.europower-energi.no|arrangement.europower-energi.no>*\n*<https://arrangement.europower-energi.no/-temporary-slug-0b75e956-b65d-47b9-bc2a-9ff4d7abb2b1|CLEAN 6-1 - LP - Opt 09 - Icon Rows>*\nCLEAN 6-1 - LP - Opt 09 - Icon Rows"
  }
]