[
  {
    "poster": {
      "poster_name": "Vishal Deep Kanojia",
      "poster_handle": "vishal.deep"
    },
    "time_stamp": "2020-01-07 02:59:24",
    "text": "Thanks <@UEKMY50SU> "
  },
  {
    "poster": {
      "poster_name": "Vincent Journel",
      "poster_handle": "vincent507"
    },
    "time_stamp": "2020-01-07 23:11:42",
    "edited": {
      "time_stamp": "2020-01-07 23:13:05"
    },
    "text": "Hello,\nI need to integrate content by an API and i want to render content on dynamics page.\nFor exemple: With my API i have list of product and i want to render a product displayed block in list. When i clic on display i want to go to one page to render the full content of my product page.\n\nIt’s possible to do that without to create a HubDB ? <https://designers.HubSpot.com/docs/tutorials/how-to-build-dynamic-pages-with-hubdb>",
    "reply_count": 2,
    "reply_users_count": 2,
    "replies": [
      {
        "time_stamp": "2020-01-08 00:47:27"
      },
      {
        "time_stamp": "2020-01-08 07:03:04"
      }
    ]
  },
  {
    "poster": {
      "poster_name": "David Duymelinck",
      "poster_handle": "david.duymelinck"
    },
    "time_stamp": "2020-01-08 00:47:27",
    "text": "You could use the CMS page publishing API. On the overview page you have a module with a field that contains all the teaser information you want to show. And with the hubl `formjson` filter you create the markup and content. You can create, update and delete the product pages with the same API."
  }
]