[
  {
    "poster": {
      "poster_name": "Roberto pacheco",
      "poster_handle": "roberto"
    },
    "time_stamp": "2019-08-21 15:11:18",
    "edited": {
      "time_stamp": "2019-08-21 15:11:51"
    },
    "text": "hi, some time ago i saw a press with a \"marketers friendly way to update/edit a hubdb\"... how is that development, when we can see that on beta?"
  },
  {
    "poster": {
      "poster_name": "Jon Miller",
      "poster_handle": "jon748"
    },
    "time_stamp": "2019-08-21 15:23:22",
    "text": "i currently have clients (marketers) updating HubDB data within the HubSpot UI and haven't heard any complaints. its a pretty straight forward UX IMO. But I am not sure if this is what you are referencing or not."
  },
  {
    "poster": {
      "poster_name": "Remington Begg",
      "poster_handle": "remingtonbegg"
    },
    "time_stamp": "2019-08-21 17:26:22",
    "text": "Same here, haven’t heard any problems from our clients/marketers"
  },
  {
    "poster": {
      "poster_name": "dennis edson",
      "poster_handle": "dennis261"
    },
    "time_stamp": "2019-08-21 18:18:29",
    "text": "I have complaints. For sure. Sorting by column, grouping would be huge ux improvements"
  },
  {
    "poster": {
      "poster_name": "Chad Pierce",
      "poster_handle": "chadbluleadz"
    },
    "time_stamp": "2019-08-21 19:40:42",
    "text": "Sortying or re ordering is the biggest complaint"
  }
]