[
  {
    "poster": {
      "poster_name": "Guy Paikowsky",
      "poster_handle": "guypaikowsky"
    },
    "time_stamp": "2024-08-06 06:03:40",
    "edited": {
      "time_stamp": "2024-08-06 06:50:13"
    },
    "text": "Is there any reason an <Icon>  might not work inside an Island?",
    "reply_count": 3,
    "reply_users_count": 2,
    "replies": [
      {
        "time_stamp": "2024-08-06 15:27:54"
      },
      {
        "time_stamp": "2024-08-08 06:47:12"
      },
      {
        "time_stamp": "2024-08-08 06:48:15"
      }
    ]
  },
  {
    "poster": {
      "poster_name": "Marcus Shannon",
      "poster_handle": "mshannon"
    },
    "time_stamp": "2024-08-06 06:09:41",
    "text": "Hello, can you provide me your portalId in a DM?"
  },
  {
    "poster": {
      "poster_name": "Marianne",
      "poster_handle": "marianne680"
    },
    "time_stamp": "2024-08-06 06:21:59",
    "text": "sent :slightly_smiling_face:"
  },
  {
    "poster": {
      "poster_name": "Andrey Kondratyuk",
      "poster_handle": "andrey"
    },
    "time_stamp": "2024-08-06 07:32:01",
    "text": "thanks for this data fetching explanation <@UAYBXDG4U> <https://www.youtube.com/watch?v=N0arXQOyfXo>. This will definitely be useful"
  },
  {
    "poster": {
      "poster_name": "Miguel Riesco",
      "poster_handle": "miguel.riesco"
    },
    "time_stamp": "2024-08-06 14:06:45",
    "text": "Hello community! I'm new here, for some context: I'm struggling to set up a new react based cms for my company based on dynamic components that can insert into DnD templates and edit the content of them from the HS edit pages.\nI'm doing some tests and I'm encountering problems to make some libraries like swiper or react-slick work, but I'm not able to make them work, I guess it has something to do with the environment is a SSR, is this correct? is there any way to make this kind of libraries work?\nBest regards and thanks for your time!",
    "reply_count": 8,
    "reply_users_count": 3,
    "replies": [
      {
        "time_stamp": "2024-08-06 15:45:06"
      },
      {
        "time_stamp": "2024-08-06 16:31:59"
      },
      {
        "time_stamp": "2024-08-06 16:33:44"
      },
      {
        "time_stamp": "2024-08-07 07:14:38"
      },
      {
        "time_stamp": "2024-08-07 07:15:11"
      },
      {
        "time_stamp": "2024-08-07 07:15:44"
      },
      {
        "time_stamp": "2024-08-07 07:16:22"
      },
      {
        "time_stamp": "2024-08-07 08:49:18"
      }
    ]
  },
  {
    "poster": {
      "poster_name": "Dennis K",
      "poster_handle": "dennis579"
    },
    "time_stamp": "2024-08-06 15:27:54",
    "text": "Could be when the Island has another layer of initial hidden content where the Icon component is used in. Not only the Icon comp will stop working but every HS Component will stop working.\n\nIf it’s just inside an (Island) element which is visible during page load, then it should work. Just remember to 10 times double check the fieldPath haha."
  },
  {
    "poster": {
      "poster_name": "Jon Miller",
      "poster_handle": "jon894"
    },
    "time_stamp": "2024-08-06 15:45:06",
    "text": "Hey <@U07FKRKDUMB>, excited to have you in the community! Could you share specifics on the problems you are encountering?"
  },
  {
    "poster": {
      "poster_name": "Miguel Riesco",
      "poster_handle": "miguel.riesco"
    },
    "time_stamp": "2024-08-06 16:31:59",
    "edited": {
      "time_stamp": "2024-08-06 16:32:19"
    },
    "text": "For example, in these libraries the buttons to make the movement do not work.\nNow for example I'm trying to use `Material-UI` and I get a more precise error:\n```[vite] Error when evaluating SSR module {path}/lp-project/lp-app/components/modules/000-lp-kit-react-base/index: failed to import \"/node_modules/@mui/icons-material/ExpandMore.js\"\n|- ReferenceError: exports is not defined\n    at eval ({path}/lp-project/lp-app/node_modules/@mui/icons-material/utils/createSvgIcon.js:8:23)\n    at async instantiateModule ({path}/lp-project/lp-app/node_modules/vite/dist/node/chunks/dep-41cf5ffd.js:56052:9)```"
  },
  {
    "poster": {
      "poster_name": "Miguel Riesco",
      "poster_handle": "miguel.riesco"
    },
    "time_stamp": "2024-08-06 16:33:44",
    "text": "In other cases I have tried using useEffect and it doesn't work either, it is something that has happened to me in other projects and it is related to the SSR issue but here I don't know how to avoid this"
  }
]