[
  {
    "poster": {
      "poster_name": "Jon K. Wheeler",
      "poster_handle": "jon.k.wheeler"
    },
    "time_stamp": "2019-08-21 09:09:37",
    "text": "how are you fetching the data?"
  },
  {
    "poster": {
      "poster_name": "Teun Rutten",
      "poster_handle": "teun"
    },
    "time_stamp": "2019-08-21 23:55:12",
    "text": "A simple fetch call using the HubSpot API"
  },
  {
    "poster": {
      "poster_name": "Teun Rutten",
      "poster_handle": "teun"
    },
    "time_stamp": "2019-08-21 23:55:48",
    "text": "But the fetch itself isn't the problem. When I use this app in a sandbox portal it works just fine, so some HubSpot code is blocking our app from rendering the right way"
  },
  {
    "poster": {
      "poster_name": "Teun Rutten",
      "poster_handle": "teun"
    },
    "time_stamp": "2019-08-22 00:20:08",
    "text": "I found the problem"
  },
  {
    "poster": {
      "poster_name": "Teun Rutten",
      "poster_handle": "teun"
    },
    "time_stamp": "2019-08-22 00:20:43",
    "edited": {
      "time_stamp": "2019-08-22 00:44:19"
    },
    "text": "An old HubSpot js file that was loaded blocked the React functionality somehow (theme-foundation-v-1-0.min.js)"
  }
]