[
  {
    "poster": {
      "poster_name": "Nicholas Decker - Level -22",
      "poster_handle": "nickdeckerdevs"
    },
    "time_stamp": "2017-02-03 08:53:25",
    "text": "anyone know how to turn off CSS minification in HubSpot?"
  },
  {
    "poster": {
      "poster_name": "Nicholas Decker - Level -22",
      "poster_handle": "nickdeckerdevs"
    },
    "time_stamp": "2017-02-03 08:55:40",
    "text": "I have sourcemaps from my sass and I have them uploading to HubSpot via ftp for the pages i'm working on but it minifies it and I don't get the value of the sourcemaps"
  },
  {
    "poster": {
      "poster_name": "normschurdell",
      "poster_handle": "normschurdell"
    },
    "time_stamp": "2017-02-03 09:38:56",
    "text": "<@U25PYL3Q8> are you looking for them in the source console when inspecting?"
  },
  {
    "poster": {
      "poster_name": "Nicholas Decker - Level -22",
      "poster_handle": "nickdeckerdevs"
    },
    "time_stamp": "2017-02-03 09:44:52",
    "text": "no, inside inpect element.. instead of the styles.css file it will display module.scss or page.scss"
  },
  {
    "poster": {
      "poster_name": "normschurdell",
      "poster_handle": "normschurdell"
    },
    "time_stamp": "2017-02-03 09:51:31",
    "text": "okay, gotcha. not sure how that is done yet"
  },
  {
    "poster": {
      "poster_name": "Gregory Cornelius",
      "poster_handle": "gcornelius"
    },
    "time_stamp": "2017-02-03 12:13:07",
    "text": "you can append `?hsDebug=true` to the url when loading the page"
  },
  {
    "poster": {
      "poster_name": "Nicholas Decker - Level -22",
      "poster_handle": "nickdeckerdevs"
    },
    "time_stamp": "2017-02-03 12:13:42",
    "text": "thanks"
  },
  {
    "poster": {
      "poster_name": "Nicholas Decker - Level -22",
      "poster_handle": "nickdeckerdevs"
    },
    "time_stamp": "2017-02-03 12:13:45",
    "text": "that will do it"
  },
  {
    "poster": {
      "poster_name": "Nicholas Decker - Level -22",
      "poster_handle": "nickdeckerdevs"
    },
    "time_stamp": "2017-02-03 12:13:51",
    "text": "can't believe i forgot that"
  },
  {
    "poster": {
      "poster_name": "Gregory Cornelius",
      "poster_handle": "gcornelius"
    },
    "time_stamp": "2017-02-03 12:14:37",
    "text": "np"
  },
  {
    "poster": {
      "poster_name": "Adrian C. Black",
      "poster_handle": "adriancblack"
    },
    "time_stamp": "2017-02-03 12:39:15",
    "text": "can anyone tell me why in a hubdb table the bold text is stripped out from the rich text field?"
  },
  {
    "poster": {
      "poster_name": "Nicholas Decker - Level -22",
      "poster_handle": "nickdeckerdevs"
    },
    "time_stamp": "2017-02-03 12:41:31",
    "text": "is it stripping out the code ?"
  },
  {
    "poster": {
      "poster_name": "Nicholas Decker - Level -22",
      "poster_handle": "nickdeckerdevs"
    },
    "time_stamp": "2017-02-03 12:41:38",
    "text": "are you using &lt;b&gt; or &lt;strong&gt;"
  },
  {
    "text": "<@U2PDTMH53|adriancblack> uploaded a file: <https://HubSpotdev.slack.com/files/adriancblack/F40T6LX52/screen_shot_2017-02-03_at_19.42.00.jpg|i can't see the html view>",
    "time_stamp": "2017-02-03 12:42:32"
  },
  {
    "poster": {
      "poster_name": "Adrian C. Black",
      "poster_handle": "adriancblack"
    },
    "time_stamp": "2017-02-03 12:43:44",
    "text": "inspecting the page, i only se an opening and closing &lt;p&gt;"
  },
  {
    "poster": {
      "poster_name": "Nicholas Decker - Level -22",
      "poster_handle": "nickdeckerdevs"
    },
    "time_stamp": "2017-02-03 12:43:51",
    "text": "I think I had a problem with that, also"
  },
  {
    "poster": {
      "poster_name": "Nicholas Decker - Level -22",
      "poster_handle": "nickdeckerdevs"
    },
    "time_stamp": "2017-02-03 12:44:15",
    "text": "I had teh code imported and I believe I had the same issue. I tried it a few times and it didnt' work so I just carried on."
  },
  {
    "poster": {
      "poster_name": "Nicholas Decker - Level -22",
      "poster_handle": "nickdeckerdevs"
    },
    "time_stamp": "2017-02-03 12:44:31",
    "text": "I was trying to bold the whole line"
  },
  {
    "poster": {
      "poster_name": "Nicholas Decker - Level -22",
      "poster_handle": "nickdeckerdevs"
    },
    "time_stamp": "2017-02-03 12:44:38",
    "text": "So I'm going to guess there is an issue with it"
  },
  {
    "poster": {
      "poster_name": "Nicholas Decker - Level -22",
      "poster_handle": "nickdeckerdevs"
    },
    "time_stamp": "2017-02-03 12:44:56",
    "text": "i'd hceck to see how it outputs to a website page"
  },
  {
    "poster": {
      "poster_name": "Adrian C. Black",
      "poster_handle": "adriancblack"
    },
    "time_stamp": "2017-02-03 12:45:36",
    "text": "i’m looking at the preview of the template and comes out as just a &lt;p&gt;"
  },
  {
    "poster": {
      "poster_name": "Adrian C. Black",
      "poster_handle": "adriancblack"
    },
    "time_stamp": "2017-02-03 12:46:38",
    "text": "also, once i click the update button in hubdb and go to the same field again, the bold is gone"
  },
  {
    "poster": {
      "poster_name": "Adrian C. Black",
      "poster_handle": "adriancblack"
    },
    "time_stamp": "2017-02-03 12:47:44",
    "text": "what’s the point of a rich text field if the “rich” bit is removed? :slightly_smiling_face:"
  },
  {
    "poster": {
      "poster_name": "normschurdell",
      "poster_handle": "normschurdell"
    },
    "time_stamp": "2017-02-03 13:01:57",
    "text": "we had similar problems back in October on a very large database build ;("
  },
  {
    "poster": {
      "poster_name": "Remington Begg",
      "poster_handle": "remingtonbegg"
    },
    "time_stamp": "2017-02-03 13:04:13",
    "text": "I was having that problem and it seemed to strip out the bold, but turned out that it wasn't updating if I didn't click on the \"update\" text vs the edge of the button..."
  },
  {
    "poster": {
      "poster_name": "Adrian C. Black",
      "poster_handle": "adriancblack"
    },
    "time_stamp": "2017-02-03 13:10:10",
    "text": "so basically the rich text field can't be used?"
  },
  {
    "poster": {
      "poster_name": "Remington Begg",
      "poster_handle": "remingtonbegg"
    },
    "time_stamp": "2017-02-03 13:51:27",
    "text": "It worked for me, just was kind of buggy"
  },
  {
    "poster": {
      "poster_name": "Adrian C. Black",
      "poster_handle": "adriancblack"
    },
    "time_stamp": "2017-02-03 13:52:02",
    "text": "can you send a screenshot? :slightly_smiling_face:",
    "reply_count": 3,
    "reply_users_count": 2,
    "replies": [
      {
        "time_stamp": "2017-02-03 13:52:31"
      },
      {
        "time_stamp": "2017-02-03 13:53:31"
      },
      {
        "time_stamp": "2017-02-03 13:55:38"
      }
    ]
  },
  {
    "poster": {
      "poster_name": "Remington Begg",
      "poster_handle": "remingtonbegg"
    },
    "time_stamp": "2017-02-03 13:52:31",
    "text": "adriancblack: of what specifically would you like?"
  },
  {
    "poster": {
      "poster_name": "Adrian C. Black",
      "poster_handle": "adriancblack"
    },
    "time_stamp": "2017-02-03 13:53:31",
    "text": "the click bit you mentioned"
  },
  {
    "poster": {
      "poster_name": "Adrian C. Black",
      "poster_handle": "adriancblack"
    },
    "time_stamp": "2017-02-03 13:55:38",
    "text": "got it :slightly_smiling_face:"
  },
  {
    "poster": {
      "poster_name": "Adrian C. Black",
      "poster_handle": "adriancblack"
    },
    "time_stamp": "2017-02-03 13:56:47",
    "text": "got it: Click at the end of the text to remove the highlight … then the changes will get saved :wink:"
  },
  {
    "poster": {
      "poster_name": "Reg Desgroseilliers",
      "poster_handle": "reg"
    },
    "time_stamp": "2017-02-03 14:02:30",
    "text": "All forms on HubSpot websites are down right now?"
  },
  {
    "poster": {
      "poster_name": "Reg Desgroseilliers",
      "poster_handle": "reg"
    },
    "time_stamp": "2017-02-03 14:03:50",
    "text": "nvm, back now"
  },
  {
    "poster": {
      "poster_name": "Jeffrey Vocell",
      "poster_handle": "jvocell"
    },
    "time_stamp": "2017-02-03 14:03:55",
    "text": "Forms seem to be working / showing up for me <@U2H1Q3F8R>"
  },
  {
    "poster": {
      "poster_name": "Jeffrey Vocell",
      "poster_handle": "jvocell"
    },
    "time_stamp": "2017-02-03 14:04:00",
    "text": "Ah, nvm."
  },
  {
    "poster": {
      "poster_name": "Reg Desgroseilliers",
      "poster_handle": "reg"
    },
    "time_stamp": "2017-02-03 14:04:10",
    "text": "they were just down on all our sites for like 10minutes?"
  },
  {
    "poster": {
      "poster_name": "Jeffrey Vocell",
      "poster_handle": "jvocell"
    },
    "time_stamp": "2017-02-03 14:04:30",
    "edited": {
      "time_stamp": "2017-02-03 14:04:45"
    },
    "text": "In case you haven’t seen this, good spot to check in situations like that: <https://status.HubSpot.com/>"
  },
  {
    "poster": {
      "poster_name": "Reg Desgroseilliers",
      "poster_handle": "reg"
    },
    "time_stamp": "2017-02-03 14:05:22",
    "text": "All Systems Operational!"
  }
]