[
  {
    "text": "Feature request - Ability to specify what edit buttons are available for use. These options write inline styles which break branding guidelines. So I either have to wipe out inline styles with javascript or use !Important in parent stylesheet.",
    "time_stamp": "2020-05-14 09:09:26",
    "reply_count": 2,
    "reply_users_count": 2,
    "replies": [
      {
        "time_stamp": "2020-05-14 09:14:07"
      },
      {
        "time_stamp": "2020-05-14 09:14:48"
      }
    ]
  },
  {
    "poster": {
      "poster_name": "AJ LaPorte",
      "poster_handle": "ajlaporte"
    },
    "time_stamp": "2020-05-14 09:14:07",
    "text": "Hey Jacob, a few messages up <@UA7JFQSQ0> mentions this: <https://HubSpotdev.slack.com/archives/CFPRTEGTX/p1589383128161900> Would you be able to post in that thread you thoughts regarding the question?"
  },
  {
    "poster": {
      "poster_name": "Jake Lett",
      "poster_handle": "jacoblett"
    },
    "time_stamp": "2020-05-14 09:14:48",
    "text": "sure thank you AJ"
  },
  {
    "poster": {
      "poster_name": "Jake Lett",
      "poster_handle": "jacoblett"
    },
    "time_stamp": "2020-05-14 09:27:33",
    "text": "I think providing a list to show would be nice. That way if something new is added it can be vetted before released in the wild. Would these settings be for each instance or is it a global setting?\n\nPersonally I would just have a need for a global setting.\n\nThank you for considering this update because currently it is causing a lot of confusion and page edits to correct."
  },
  {
    "poster": {
      "poster_name": "Jake Lett",
      "poster_handle": "jacoblett"
    },
    "time_stamp": "2020-05-14 09:29:24",
    "text": "I think providing a list to show would be nice. That way if something new is added it can be vetted before released in the wild.\n\nWould these settings be for each instance or is it a global setting?Personally I would just have a need for a global setting.\n\nThank you for considering this update because currently it is causing a lot of confusion and page edits to correct."
  },
  {
    "poster": {
      "poster_name": "Katie Tade",
      "poster_handle": "ktade"
    },
    "time_stamp": "2020-05-14 11:35:36",
    "text": "We’re starting by having it just set at the module instance since that’s more at the MVP level for us, but we’re considering how we can make it more global. The only problem with a global setting is that each toolbar is a little different and might have different controls, so we just need to make sure we handle that the right way."
  },
  {
    "poster": {
      "poster_name": "Trey",
      "poster_handle": "trey185"
    },
    "time_stamp": "2020-05-14 14:45:25",
    "edited": {
      "time_stamp": "2020-05-14 14:47:28"
    },
    "text": "is anyone seeing an issue with extra spacing in design manager when using bool checkboxes in custom modules?",
    "reply_count": 8,
    "reply_users_count": 2,
    "replies": [
      {
        "time_stamp": "2020-05-15 10:57:26"
      },
      {
        "time_stamp": "2020-05-16 11:54:07"
      },
      {
        "time_stamp": "2020-05-16 14:21:51"
      },
      {
        "time_stamp": "2020-05-16 14:22:09"
      },
      {
        "time_stamp": "2020-05-16 14:22:37"
      },
      {
        "time_stamp": "2020-05-16 14:52:15"
      },
      {
        "time_stamp": "2020-05-16 18:52:26"
      },
      {
        "time_stamp": "2020-05-18 09:43:21"
      }
    ]
  },
  {
    "text": "",
    "time_stamp": "2020-05-14 14:45:30"
  },
  {
    "poster": {
      "poster_name": "Trey",
      "poster_handle": "trey185"
    },
    "time_stamp": "2020-05-14 14:46:01",
    "text": "this happens on safari and chrome as of today... has not been doing this in the past and there has been no changes to the module source"
  }
]