[
  {
    "poster": {
      "poster_name": "Patrick Keo",
      "poster_handle": "patrick362"
    },
    "time_stamp": "2022-04-20 07:16:03",
    "text": "Hi there, can someone point me to a tutorial or discussion about how to get a sticky side menu item to become active on scroll when going past an anchor on a drag and drop page? I have looked at different pens and on stackoverflow but can't seem to find anything that will work in HubSpot. I have the sticky side menu working fine, it's just the active isn't being applied when scrolling past the anchored modules.",
    "reply_count": 1,
    "reply_users_count": 1,
    "replies": [
      {
        "time_stamp": "2022-04-20 08:30:48"
      }
    ]
  },
  {
    "poster": {
      "poster_name": "BJ Szyjakowski",
      "poster_handle": "bj.s"
    },
    "time_stamp": "2022-04-20 08:30:48",
    "text": "Hey Patrick — you will need to write some JS that watches for when those anchors reach a certain point on the viewport"
  }
]