[
  {
    "poster": {
      "poster_name": "Samriti Chandel",
      "poster_handle": "samriti.chandel"
    },
    "time_stamp": "2019-10-15 06:05:20",
    "text": "How can i add a custom code to My custom Template.",
    "reply_count": 4,
    "reply_users_count": 1,
    "replies": [
      {
        "time_stamp": "2019-10-16 22:09:15"
      },
      {
        "time_stamp": "2019-10-16 22:09:56"
      },
      {
        "time_stamp": "2019-10-16 22:10:26"
      },
      {
        "time_stamp": "2019-10-16 22:10:41"
      }
    ]
  },
  {
    "poster": {
      "poster_name": "Samriti Chandel",
      "poster_handle": "samriti.chandel"
    },
    "time_stamp": "2019-10-15 06:05:43",
    "text": "Like i want to create a custom dropdown"
  },
  {
    "poster": {
      "poster_name": "Jonathan Stanis",
      "poster_handle": "jstanis"
    },
    "time_stamp": "2019-10-15 12:07:42",
    "text": "Anyone ever have a main menu break? The main navigation on this page has broken and I can’t figure out why. We didn’t change anything on the site. <https://www.huimfg.com/?hsCacheBuster=4156>",
    "reply_count": 18,
    "reply_users_count": 4,
    "replies": [
      {
        "time_stamp": "2019-10-15 12:11:14"
      },
      {
        "time_stamp": "2019-10-15 12:13:04"
      },
      {
        "time_stamp": "2019-10-15 12:14:38"
      },
      {
        "time_stamp": "2019-10-15 12:15:12"
      },
      {
        "time_stamp": "2019-10-16 01:25:05"
      },
      {
        "time_stamp": "2019-10-16 07:28:44"
      },
      {
        "time_stamp": "2019-10-16 07:38:24"
      },
      {
        "time_stamp": "2019-10-16 07:39:16"
      },
      {
        "time_stamp": "2019-10-16 07:40:25"
      },
      {
        "time_stamp": "2019-10-16 07:40:38"
      },
      {
        "time_stamp": "2019-10-16 10:31:46"
      },
      {
        "time_stamp": "2019-10-16 10:33:33"
      },
      {
        "time_stamp": "2019-10-16 11:17:57"
      },
      {
        "time_stamp": "2019-10-16 11:19:58"
      },
      {
        "time_stamp": "2019-10-16 11:21:29"
      },
      {
        "time_stamp": "2019-10-16 11:22:02"
      },
      {
        "time_stamp": "2019-10-17 07:04:45"
      },
      {
        "time_stamp": "2019-10-17 07:18:45"
      }
    ]
  },
  {
    "poster": {
      "poster_name": "Zack Wolfson",
      "poster_handle": "zwolfson"
    },
    "time_stamp": "2019-10-15 12:11:14",
    "text": "Looks like it reverted to a sample menu. It’s possible someone changed the menu the module is using without realizing it"
  },
  {
    "poster": {
      "poster_name": "Zack Wolfson",
      "poster_handle": "zwolfson"
    },
    "time_stamp": "2019-10-15 12:13:04",
    "text": "If you go into the template that controls that page and find the menu module (generally it’s in a global group), you can change the which menu the module is using"
  },
  {
    "poster": {
      "poster_name": "Jonathan Stanis",
      "poster_handle": "jstanis"
    },
    "time_stamp": "2019-10-15 12:14:38",
    "text": "The menu in the global group did not change. I changed it to something else to see if that would make a difference and it did not."
  },
  {
    "poster": {
      "poster_name": "Zack Wolfson",
      "poster_handle": "zwolfson"
    },
    "time_stamp": "2019-10-15 12:15:12",
    "text": "hmm, can you direct message your portal id and I can take a look and see what might be the issue?"
  },
  {
    "poster": {
      "poster_name": "Steven Hambleton",
      "poster_handle": "steven994"
    },
    "time_stamp": "2019-10-15 21:55:28",
    "text": "You can reduce that a little with -\n`padding: 10px 20px;`"
  }
]