[
  {
    "text": "I'm playing with the idea of presenting a dropdown for the editors that *display colors* in the dropdown instead of text.\nWhat I get VS what I want:",
    "time_stamp": "2023-01-26 06:41:57",
    "reply_count": 6,
    "reply_users_count": 2,
    "replies": [
      {
        "time_stamp": "2023-01-26 06:44:10"
      },
      {
        "time_stamp": "2023-01-26 06:45:42"
      },
      {
        "time_stamp": "2023-01-26 06:47:55"
      },
      {
        "time_stamp": "2023-01-31 14:49:43"
      },
      {
        "time_stamp": "2023-01-31 14:51:12"
      },
      {
        "time_stamp": "2023-01-31 14:57:19"
      }
    ]
  },
  {
    "text": "I tried a dirty inline style on the \"text part of the \"choice\" field like this:",
    "time_stamp": "2023-01-26 06:44:10"
  },
  {
    "text": "But it just turns into this, where the HubL doesn't do its magic",
    "time_stamp": "2023-01-26 06:45:42"
  },
  {
    "text": "To make it even more clear:\nif we look at this as a \"*key*-*value*\" pair, the *key* is the only one who gets HubL'd. Any way around this?",
    "time_stamp": "2023-01-26 06:47:55"
  }
]