[
  {
    "text": "Happy weekend folks here's a cover song for you <@U2H3TT8F2> ps. This is my apology for never getting you that blog and you're going to have it on Monday",
    "time_stamp": "2023-04-07 15:23:00",
    "reply_count": 10,
    "reply_users_count": 7,
    "replies": [
      {
        "time_stamp": "2023-04-11 14:45:15"
      },
      {
        "time_stamp": "2023-04-11 14:49:18"
      },
      {
        "time_stamp": "2023-04-11 14:51:16"
      },
      {
        "time_stamp": "2023-04-11 14:53:15"
      },
      {
        "time_stamp": "2023-04-11 15:00:47"
      },
      {
        "time_stamp": "2023-04-11 15:01:19"
      },
      {
        "time_stamp": "2023-04-11 22:09:48"
      },
      {
        "time_stamp": "2023-04-13 10:23:53"
      },
      {
        "time_stamp": "2023-04-13 10:54:54"
      },
      {
        "time_stamp": "2023-10-27 09:46:32"
      }
    ]
  }
]