[
  {
    "poster": {
      "poster_name": "Jose Nunez",
      "poster_handle": "joseenrique0595"
    },
    "time_stamp": "2022-02-01 10:22:01",
    "text": "Hi all! I’m uploading “email modules” from local to my portal, these modules are from emails but when I already upload the modules the emails are blank. What could be the issue?\nThanks!",
    "reply_count": 3,
    "reply_users_count": 2,
    "replies": [
      {
        "time_stamp": "2022-02-02 09:05:12"
      },
      {
        "time_stamp": "2022-02-02 10:34:24"
      },
      {
        "time_stamp": "2022-02-02 10:43:29"
      }
    ]
  }
]