[
  {
    "poster": {
      "poster_name": "Michael Niemeijer",
      "poster_handle": "michael915"
    },
    "time_stamp": "2021-11-02 04:26:29",
    "text": "Hi all! Can’t seem to find how to create my own email d&amp;d template. Know how to create modules for it. Just want to create a email d&amp;d template to put some css custom for mobile in it.. somebody knows how to set this up?",
    "reply_count": 2,
    "reply_users_count": 2,
    "replies": [
      {
        "time_stamp": "2021-11-02 04:31:11"
      },
      {
        "time_stamp": "2021-11-02 09:05:41"
      }
    ]
  },
  {
    "text": "found my answer:",
    "time_stamp": "2021-11-02 04:31:11"
  },
  {
    "poster": {
      "poster_name": "Courtney Fantinato",
      "poster_handle": "courtneyfantinato"
    },
    "time_stamp": "2021-11-02 09:05:41",
    "text": "Custom modules can be used with DND emails, however there is no way to control the mobile styles of emails made with the DND editor."
  }
]