[
  {
    "poster": {
      "poster_name": "Jon McLaren",
      "poster_handle": "jon558"
    },
    "time_stamp": "2019-04-16 13:32:09",
    "text": "Anyone tried using their keyboard to navigate the chrome extension’s popup?\n\nI’ve kinda always wanted to make it more accessible/keyboard friendly just never really felt that many people would use it"
  },
  {
    "poster": {
      "poster_name": "dennis edson",
      "poster_handle": "dennis261"
    },
    "time_stamp": "2019-04-16 13:33:18",
    "text": "i have longed for a keyboard shortcut for the cache buster"
  },
  {
    "poster": {
      "poster_name": "Jon McLaren",
      "poster_handle": "jon558"
    },
    "time_stamp": "2019-04-16 14:19:08",
    "text": "hah, well you’ve longed long enough"
  },
  {
    "poster": {
      "poster_name": "Jon McLaren",
      "poster_handle": "jon558"
    },
    "time_stamp": "2019-04-16 14:19:39",
    "text": "That’s already a thing.\n<https://github.com/TheWebTech/HubSpot-Developer-Extension/wiki/How-to-Use-and-set-up-Keyboard-Shortcuts>"
  },
  {
    "poster": {
      "poster_name": "Jon McLaren",
      "poster_handle": "jon558"
    },
    "time_stamp": "2019-04-16 14:20:06",
    "text": "I was meaning more for within the popup itself, but lol I’m fine exploring more ways to use keyboard shortcuts in the extension"
  },
  {
    "poster": {
      "poster_name": "dennis edson",
      "poster_handle": "dennis261"
    },
    "time_stamp": "2019-04-16 14:35:16",
    "text": "hello hello"
  },
  {
    "poster": {
      "poster_name": "Jon McLaren",
      "poster_handle": "jon558"
    },
    "time_stamp": "2019-04-16 14:41:51",
    "text": "at a place called vertigo :musical_note:"
  }
]